automation/__init__.py
automation/chrome_factory.py
automation/chrome_manager.py
automation/chrome_singleton.py
azucar_web_driver/__init__.py
azucar_web_driver/chrome_factory.py
azucar_web_driver/chrome_manager.py
azucar_web_driver/chrome_singleton.py
azucar_web_driver-0.1.dist-info/METADATA
azucar_web_driver-0.1.dist-info/WHEEL
azucar_web_driver-0.1.dist-info/top_level.txt
azucar_web_driver-0.1.dist-info/RECORD
